LICENSE
MANIFEST.in
README.md
pyproject.toml
setup.py
discretizer/__init__.py
discretizer/digger.py
discretizer/geometrical_objects.py
discretizer/io.py
discretizer/linalg.py
discretizer/minimal_enclosing.py
discretizer/tunnel.py
discretizer/tunnel_curve.py
discretizer.egg-info/PKG-INFO
discretizer.egg-info/SOURCES.txt
discretizer.egg-info/dependency_links.txt
discretizer.egg-info/requires.txt
discretizer.egg-info/top_level.txt
ext/minball/minball.cpp
ext/minball/minball.hpp
scripts/discretizer