Metadata-Version: 2.1
Name: discretizer
Version: 1.1.0
Summary: Tool for transformation of protein tunnels represented by spheres to a sequence of disks
Home-page: https://github.com/loschmidt/discretizer
Author: Jan Plhak
Author-email: 408420@mail.muni.cz
License: UNKNOWN
Platform: UNKNOWN
Classifier: Programming Language :: Python :: 3 :: Only
Classifier: License :: OSI Approved :: GNU Lesser General Public License v3 or later (LGPLv3+)
Classifier: Operating System :: OS Independent
Classifier: Environment :: Console
